cdktf_cdktf_provider_okta/__init__.py
cdktf_cdktf_provider_okta/py.typed
cdktf_cdktf_provider_okta/_jsii/__init__.py
cdktf_cdktf_provider_okta/_jsii/provider-okta@14.1.0.jsii.tgz
cdktf_cdktf_provider_okta/admin_role_custom/__init__.py
cdktf_cdktf_provider_okta/admin_role_custom_assignments/__init__.py
cdktf_cdktf_provider_okta/admin_role_targets/__init__.py
cdktf_cdktf_provider_okta/app_access_policy_assignment/__init__.py
cdktf_cdktf_provider_okta/app_auto_login/__init__.py
cdktf_cdktf_provider_okta/app_basic_auth/__init__.py
cdktf_cdktf_provider_okta/app_bookmark/__init__.py
cdktf_cdktf_provider_okta/app_group_assignment/__init__.py
cdktf_cdktf_provider_okta/app_group_assignments/__init__.py
cdktf_cdktf_provider_okta/app_oauth/__init__.py
cdktf_cdktf_provider_okta/app_oauth_api_scope/__init__.py
cdktf_cdktf_provider_okta/app_oauth_post_logout_redirect_uri/__init__.py
cdktf_cdktf_provider_okta/app_oauth_redirect_uri/__init__.py
cdktf_cdktf_provider_okta/app_oauth_role_assignment/__init__.py
cdktf_cdktf_provider_okta/app_saml/__init__.py
cdktf_cdktf_provider_okta/app_saml_app_settings/__init__.py
cdktf_cdktf_provider_okta/app_secure_password_store/__init__.py
cdktf_cdktf_provider_okta/app_shared_credentials/__init__.py
cdktf_cdktf_provider_okta/app_signon_policy/__init__.py
cdktf_cdktf_provider_okta/app_signon_policy_rule/__init__.py
cdktf_cdktf_provider_okta/app_swa/__init__.py
cdktf_cdktf_provider_okta/app_three_field/__init__.py
cdktf_cdktf_provider_okta/app_user/__init__.py
cdktf_cdktf_provider_okta/app_user_base_schema_property/__init__.py
cdktf_cdktf_provider_okta/app_user_schema_property/__init__.py
cdktf_cdktf_provider_okta/auth_server/__init__.py
cdktf_cdktf_provider_okta/auth_server_claim/__init__.py
cdktf_cdktf_provider_okta/auth_server_claim_default/__init__.py
cdktf_cdktf_provider_okta/auth_server_default/__init__.py
cdktf_cdktf_provider_okta/auth_server_policy/__init__.py
cdktf_cdktf_provider_okta/auth_server_policy_rule/__init__.py
cdktf_cdktf_provider_okta-14.1.0.dist-info/LICENSE
cdktf_cdktf_provider_okta-14.1.0.dist-info/METADATA
cdktf_cdktf_provider_okta-14.1.0.dist-info/WHEEL
cdktf_cdktf_provider_okta-14.1.0.dist-info/top_level.txt
cdktf_cdktf_provider_okta-14.1.0.dist-info/RECORD
